datadb3
minidb
